{"data":{"_id":1000,"properties":{"catId":{"name":"catId","kind":"scalar","primary":true,"fieldNames":["cat_id"],"type":"number","array":false,"runtimeType":"number"},"catName":{"name":"catName","kind":"scalar","getter":false,"setter":false,"fieldNames":["cat_name"],"type":"string","array":false,"runtimeType":"string"},"books":{"name":"books","kind":"1:m","cascade":["persist"],"type":"Book","array":false,"runtimeType":"Book"}},"primaryKeys":["catId"],"filters":{},"hooks":{},"indexes":[],"uniques":[],"className":"Category","path":"./dist/entities/category.entity.js","collection":"categories","name":"Category","abstract":false,"internal":true,"constructorParams":[],"toJsonParams":[],"useCache":true,"compositePK":false,"simplePK":true},"origin":"./dist/entities/category.entity.js","hash":"27254d5c8511778316fa6a6463d68c53","version":"6.6.15"}
